core/__init__.py
core/extensions.py
core/items.py
core/middlewares.py
core/pipelines.py
core/settings.py
core/spiders/__init__.py
core/spiders/basic_spider.py
crawl_bot-0.2.1.dist-info/METADATA
crawl_bot-0.2.1.dist-info/WHEEL
crawl_bot-0.2.1.dist-info/top_level.txt
crawl_bot-0.2.1.dist-info/RECORD
